LICENSE
MANIFEST.in
README.rst
requirements.txt
setup.cfg
setup.py
./dissertate/__init__.py
./dissertate/bibliography.py
./dissertate/dissertate.tpl
./dissertate/nb_tools.py
./dissertate/preprocessors.py
./dissertate/util.py
./tests/__init__.py
./tests/test_preprocessors.py
dissertate/dissertate.tpl
dissertate.egg-info/PKG-INFO
dissertate.egg-info/SOURCES.txt
dissertate.egg-info/dependency_links.txt
dissertate.egg-info/not-zip-safe
dissertate.egg-info/top_level.txt