Metadata-Version: 1.2
Name: dissertate
Version: 0.0.9
Summary: A package and CLI for writing dissertations.
Home-page: https://github.com/jbn/dissertate
Author: John Bjorn Nelson (generativist)
Author-email: jbn@abreka.com
Maintainer: John Bjorn Nelson (generativist)
Maintainer-email: jbn@abreka.com
License: MIT
Keywords: phd,dissertation,thesis,jupyter,ipython
Platform: UNKNOWN
Classifier: Development Status :: 3 - Alpha
Classifier: Framework :: IPython
Classifier: Intended Audience :: Science/Research
Classifier: Natural Language :: English
Classifier: License :: OSI Approved :: MIT License
Classifier: Operating System :: OS Independent
Classifier: Programming Language :: Python
Classifier: Programming Language :: Python :: 2
Classifier: Programming Language :: Python :: 2.6
Classifier: Programming Language :: Python :: 2.7
Classifier: Programming Language :: Python :: 3
Classifier: Programming Language :: Python :: 3.3
Classifier: Programming Language :: Python :: 3.4
Classifier: Programming Language :: Python :: 3.5
Classifier: Programming Language :: Python :: 3.6
Classifier: Programming Language :: Python :: Implementation :: CPython
Classifier: Programming Language :: Python :: Implementation :: PyPy
Classifier: Topic :: Software Development :: Libraries :: Python Modules
